{
  "type" : "stackView",
  "content" : {
    "orientation" : "horizontal",
    "items" : [
      
      {
        "type" : "icon", 
        "content" : {
          "icon" : "user",
          "width" : 32,
          "height" : 32
        },
        "style" : {
          "gravity" : "top",
          "marginRight" : 21
        }
      },

      {
        "type" : "stackView",
        "content" : {
          "items" : [
            {
              "type": "label",
              "content": {
                "text": "Cancelled Auto Pay",
                "fontWeight": "bold",
                "fontSize": 15,
                "color": "#57617b"
              },
              "style" : {
                "marginBottom" : 6
              }
            },

            {
              "type": "label",
              "content": {
                "text": "You have successfully removed autopay from your account",
                "fontWeight": "regular",
                "fontSize": 12,
                "color": "#646e85"
              },
              "style" : {
                "marginBottom" : 8
              }
            },

            {
              "type": "label",
              "content": {
                "text": "March 15, 2017 -- 4:15PM",
                "fontWeight": "regular",
                "fontSize": 12,
                "color": "#adb2be"
              }
            }
          ]
        }, 
        "style" : {
          "weight" : 1,
          "gravity" : "top"
        }
      }
      
    ]
  }, 
  "style" : {
    "align" : "center",
    "marginBottom" : 4,
    "padding" : 21
  }
}