{
  "body": {
    "content": {
      "items": [
        {
          "content": {
            "icon": "user"
          },
          "style": {
            "gravity": "top",
            "height": 32,
            "marginRight": 21,
            "width": 32
          },
          "type": "icon"
        },
        {
          "content": {
            "items": [
              {
                "content": {
                  "text": "Cancelled Auto Pay"
                },
                "style": {
                  "color": "#57617b",
                  "fontSize": 15,
                  "fontWeight": "bold",
                  "marginBottom": 6
                },
                "type": "label"
              },
              {
                "content": {
                  "text": "You have successfully removed autopay from your account"
                },
                "style": {
                  "color": "#646e85",
                  "fontSize": 12,
                  "fontWeight": "regular",
                  "marginBottom": 8
                },
                "type": "label"
              },
              {
                "content": {
                  "text": "March 15, 2017 -- 4:15PM"
                },
                "style": {
                  "color": "#adb2be",
                  "fontSize": 12,
                  "fontWeight": "regular"
                },
                "type": "label"
              }
            ]
          },
          "style": {
            "gravity": "top",
            "weight": 1
          },
          "type": "stackView"
        }
      ],
      "orientation": "horizontal"
    },
    "style": {
      "align": "center",
      "marginBottom": 4,
      "padding": 21
    },
    "type": "stackView"
  },
  "styles": {}
}