{
  "type": "stack_view",
  "content": {
    "items": [
      {
        "type": "stack_view",
        "content": {
          "orientation": "horizontal",
          "items": [
            {
              "type": "label",
              "content": {
                "text": "Data Usage",
                "font_weight": "black",
                "font_size": 16,
                "color": "#5b657e"
              },
              "style" : {
                "gravity": "middle"
              }
            },
            {
              "type": "button",
              "content": {
                "title": "VIEW ALL",
                "style": "text"
              },
              "style" : {
                "align": "right",
                "gravity": "middle",
                "weight": 1,
                "padding": {
                  "top": 12,
                  "left": 16,
                  "bottom": 12,
                  "right": 0
                }
              }
            }
          ]
        },
        "style" : {
          "padding": {
            "top": 4,
            "bottom": 4
          }
        }
      },
      {
        "type": "separator"
      },

      {
        "type" : "progress_bar",
        "content" : {
            "fill_percentage" : 0.98,
            "bar_height" : 10,
        },
        "style" : {
            "margin" : [20]
        }
      },
      {
        "type": "label",
        "content": {
          "text": "448 GB",
          "alignment": "center",
          "font_weight": "black",
          "font_size": 18,
          "color": "#55607a"
        },
        "style" : {
          "align": "fill",
          "margin_bottom" : 4
        }
      },

      {
        "type": "label",
        "content": {
          "text": "of 450 GB",
          "alignment": "center",
          "font_weight": "regular",
          "font_size": 12,
          "color": "#55607a"
        },
        "style" : {
          "align": "fill",
        }
      },
      
    ]
  },
  "style" : {
    "padding": [0, 20, 20, 20]
  }
}